src/nano4k_spi_flash.v
//P25Q32H command list, see datasheet page 22
`define FREAD 8'h0B //Max freq is around 120MHz
`define READ 8'h03 //Max freq allowed is around 70MHz
`define RSTEN 8'h66 //Reset Enable
`define RST 8'h99   //Soft reset
`define PP 8'h02 //page program

module nano4k_spi_flash(
                            input reset_n,
                            input interfaceEnable_n,
                            input interfaceClk,
                            input serialClk,
                            input [7:0] fCommand,
                            input [21:0] fAddress,
                            input [7:0] fData_WR,
                            output reg [7:0] fData_RD,
                            output reg RdDataValid,
                            output reg WrDataReady,

                            //flash chip pins
                            input MISO,
                            output reg MOSI,
                            output MCLK,
                            output reg CS_n
                        );
    reg[7:0] currentCmd;
    reg[7:0] writeBuffer;
    reg[23:0] currentAddr;
    reg[3:0] flashState;

    //Flash interface states
    localparam IDLE = 0;
    localparam CMD_TX = 1;
    localparam ADDR_TX = 2;
    localparam DMMY_WAIT = 3;
    localparam DATA_PHASE = 4;

    always @(posedge interfaceClk) begin
        //TODO raise an exit flag whenever the interface is about to go IDLE?
        if (!interfaceEnable_n) begin
            CS_n <= 0;
            case (flashState)
                IDLE: begin
                    currentCmd <= fCommand;
                    //chip expects 24-bit address but only need 22 bits to address the available 4MiB
                    currentAddr <= {2'b0, fAddress};
                    flashState <= CMD_TX;
                end
                CMD_TX: begin
                    if (WrDataReady) begin
                        if (cmdHasAddrPhase)  begin
                            flashState <= ADDR_TX;
                        end else if (cmdHasDmmyPhase) begin
                            flashState <= DMMY_WAIT;
                        end else if (cmdHasDataPhase) begin
                            flashState <= DATA_PHASE;
                        end else begin
                            flashState <= IDLE;
                        end
                        serializerEnable <= 0;
                    end else begin
                        serializerEnable <= 1;
                        serializerByteBuffer <= currentCmd;
                    end
                end
                ADDR_TX: begin
                    if (addrCycleCount == 3) begin
                        addrCycleCount <= 0;
                        if (cmdHasDmmyPhase) begin 
                            flashState <= DMMY_WAIT;
                        end else if (cmdHasDataPhase) begin
                            flashState <= DATA_PHASE;
                        end else begin
                            flashState <= IDLE;
                        end
                        serializerEnable <= 0;
                    end else begin
                        {serializerByteBuffer, currentAddr} <= {serializerByteBuffer, currentAddr} << 8;
                        serializerEnable <= 1;
                        addrCycleCount <= addrCycleCount + 1;
                    end 
                    
                end
                DMMY_WAIT: begin
                    //retransmit whatever is in the buffer to waste SPI clock cycles
                    if (dmmyCycleCount == numOfDmmyBytes) begin
                        serializerEnable <= 0;
                        dmmyCycleCount <= 0;
                        if (cmdHasDataPhase) begin
                            flashState <= DATA_PHASE;
                        end else begin
                            flashState <= IDLE;
                        end
                    end else begin
                        //waste MCLK cycles, data sent/received is Don't Care
                        serializerEnable <= 1;
                        dmmyCycleCount <= dmmyCycleCount + 1;
                    end
                end
                DATA_PHASE: begin
                    if (isReadCmd) begin
                        deserializerEnable <= 1;
                        if (RdDataValid) begin
                            //fData_RD <= deserializerBuffer;
                            //This isn't nice, but deserializer is one spi clock behind
                            fData_RD <= {deserializerBuffer, MISO};
                        end
                    end else begin
                        serializerEnable <= 1;
                        serializerByteBuffer <= fData_WR;
                    end
                    //deassert interfaceEnable_n to exit the array read/write
                end
            endcase
        end else begin
            flashState <= IDLE;
            serializerEnable <= 0;
            addrCycleCount <= 0;
            dmmyCycleCount <= 0;
            deserializerEnable <= 0;
            CS_n <= 1;
        end
    end

    reg[1:0] addrCycleCount;
    reg[2:0] dmmyCycleCount;
    reg[2:0] numOfDmmyBytes;

    //serializer active-low clock control
    reg serMclkEnable_n;
    //deserializer active-low clock control
    wire desMclkEnable_n = !deserializerEnable;

    //CPOL=1 idle-high SPI clock
    //MCLK active when either or both serializer/deserializer clock controls are active
    assign MCLK = serialClk | (serMclkEnable_n && desMclkEnable_n);

    reg serializerEnable;
    reg[7:0] serializerByteBuffer;
    reg[7:0] mosiOut;
    reg[3:0] serializerCycleCount;

    //serialization block
    //load output data and enable SPI clock out on cycle 0
    always@(negedge serialClk) begin
        if (serializerEnable) begin
            if (serializerCycleCount == 0) begin
                serMclkEnable_n <= 0;
                WrDataReady <= 0;
                mosiOut <= serializerByteBuffer << 1;
                MOSI <= serializerByteBuffer[7];
            end else begin
                {MOSI, mosiOut} <= {MOSI, mosiOut} << 1;
            end

            if (serializerCycleCount == 7) begin
                //raise ready flag just in time for interfaceClk domain to sample it
                WrDataReady <= 1;
                serializerCycleCount <= 0;
            end else begin 
                serializerCycleCount <= serializerCycleCount + 1;
            end
        end else begin
            mosiOut <= 0;
            serMclkEnable_n <= 1;
            WrDataReady <= 0;
            serializerCycleCount <= 0;
            MOSI <= 0;
        end
    end

    reg deserializerEnable;

    reg[3:0] deserializerCycleCount;
    reg[7:0] deserializerBuffer;
	//deserialization block
    always@(posedge serialClk) begin
        if (deserializerEnable) begin
            if (deserializerCycleCount == 0) begin
                RdDataValid <= 0;
            end
            deserializerBuffer <= {deserializerBuffer, MISO};

            if (deserializerCycleCount == 6) begin
                RdDataValid <= 1;
            end

            if (deserializerCycleCount == 7) begin
                deserializerCycleCount <= 0;
            end else begin
                deserializerCycleCount <= deserializerCycleCount + 1;
            end
        end else begin
            deserializerBuffer <= 0;
            RdDataValid <= 0;
            deserializerCycleCount <= 0;
        end
    end

    reg cmdHasAddrPhase;
    reg cmdHasDmmyPhase;
    reg cmdHasDataPhase;
    reg isReadCmd; //1 for a data read command, 0 for a data write command.
    //combinational block for determining phases required for each command
    always@(*) begin
        case(currentCmd)
            `READ: begin
                cmdHasAddrPhase = 1;
                cmdHasDmmyPhase = 0;
                cmdHasDataPhase = 1;
                isReadCmd = 1;
            end
            `FREAD: begin
                cmdHasAddrPhase = 1;
                cmdHasDmmyPhase = 1;
                cmdHasDataPhase = 1;
                isReadCmd = 1;
            end
            `PP: begin
                cmdHasAddrPhase = 1;
                cmdHasDmmyPhase = 0;
                cmdHasDataPhase = 1;
                isReadCmd = 0;
            end
            default: begin
                cmdHasAddrPhase = 0;
                cmdHasDmmyPhase = 0;
                cmdHasDataPhase = 0;
                isReadCmd = 0;
            end
        endcase
    end

    initial begin
        serializerCycleCount <= 0;
        serializerByteBuffer <= 0;
        deserializerBuffer <= 0;
        addrCycleCount <= 0;
        dmmyCycleCount <= 0;
        numOfDmmyBytes <= 1;
        serMclkEnable_n <= 1;
        WrDataReady <= 0;
        RdDataValid <= 0;
        serializerEnable <= 0;
        mosiOut <= 0;
        currentCmd <= 0; 
        MOSI <= 0;
        fData_RD <= 0;
    end
endmodule

src/nano4k_spi_flash_tb.v
`include "nano4k_spi_flash.v"
`timescale 1 ns/10 ps // time-unit = 1 ns, precision = 10 ps

module nano4k_spi_flash_tb;
    reg i_clock;
    reg s_clock;
    reg i_enable_n;
    reg[7:0] cmd;
    reg[21:0] addr;
    reg[7:0] wr_data;
    wire[7:0] rd_data;
    wire readStrobe;
    wire writeStrobe;

    reg spiMiso;
    wire spiMosi;
    wire spiClk;
    wire chipSelect;

    always #80 i_clock <= ~i_clock;
    always #10 s_clock <= ~s_clock; //8 x i_clock

    nano4k_spi_flash dut(
        .interfaceClk(i_clock),
        .serialClk(s_clock),
        .interfaceEnable_n(i_enable_n),
        .fCommand(cmd),
        .fAddress(addr),
        .fData_WR(wr_data),
        .fData_RD(rd_data),
        .RdDataValid(readStrobe),
        .WrDataReady(writeStrobe),

        .MISO(spiMiso),
        .MOSI(spiMosi),
        .MCLK(spiClk),
        .CS_n(chipSelect)
    );

    initial begin
        $dumpfile("sim_result.vcd");
        $dumpvars(0, nano4k_spi_flash_tb);
        $dumpon;

        #0 i_clock = 1;
        #0 s_clock = 1;
        #0 i_enable_n = 1;
        #0 cmd = `RSTEN;
        #0 spiMiso = 0;
        #300 i_enable_n = 0;
        #1500 i_enable_n = 1;
        #1500 cmd = `FREAD;
        #1500 addr = 22'h3A5;
        #1740 i_enable_n = 0;
        #1650 spiMiso = 1;
        #10 spiMiso = 0;
        #10 spiMiso = 1;
        #20 spiMiso = 0;
        #2990 i_enable_n = 1;
        #5400 $finish;
    end
endmodule

src/sim_result.vcd
$date
	Sun Jul 17 18:45:10 2022
$end
$version
	Icarus Verilog
$end
$timescale
	10ps
$end
$scope module nano4k_spi_flash_tb $end
$var wire 1 ! writeStrobe $end
$var wire 1 " spiMosi $end
$var wire 1 # spiClk $end
$var wire 1 $ readStrobe $end
$var wire 8 % rd_data [7:0] $end
$var wire 1 & chipSelect $end
$var reg 22 ' addr [21:0] $end
$var reg 8 ( cmd [7:0] $end
$var reg 1 ) i_clock $end
$var reg 1 * i_enable_n $end
$var reg 1 + s_clock $end
$var reg 1 , spiMiso $end
$var reg 8 - wr_data [7:0] $end
$scope module dut $end
$var wire 1 # MCLK $end
$var wire 1 , MISO $end
$var wire 22 . fAddress [21:0] $end
$var wire 8 / fCommand [7:0] $end
$var wire 8 0 fData_WR [7:0] $end
$var wire 1 ) interfaceClk $end
$var wire 1 * interfaceEnable_n $end
$var wire 1 1 reset_n $end
$var wire 1 + serialClk $end
$var wire 1 2 desMclkEnable_n $end
$var parameter 32 3 ADDR_TX $end
$var parameter 32 4 CMD_TX $end
$var parameter 32 5 DATA_PHASE $end
$var parameter 32 6 DMMY_WAIT $end
$var parameter 32 7 IDLE $end
$var reg 1 & CS_n $end
$var reg 1 " MOSI $end
$var reg 1 $ RdDataValid $end
$var reg 1 ! WrDataReady $end
$var reg 2 8 addrCycleCount [1:0] $end
$var reg 1 9 cmdHasAddrPhase $end
$var reg 1 : cmdHasDataPhase $end
$var reg 1 ; cmdHasDmmyPhase $end
$var reg 24 < currentAddr [23:0] $end
$var reg 8 = currentCmd [7:0] $end
$var reg 8 > deserializerBuffer [7:0] $end
$var reg 4 ? deserializerCycleCount [3:0] $end
$var reg 1 @ deserializerEnable $end
$var reg 3 A dmmyCycleCount [2:0] $end
$var reg 8 B fData_RD [7:0] $end
$var reg 4 C flashState [3:0] $end
$var reg 1 D isReadCmd $end
$var reg 8 E mosiOut [7:0] $end
$var reg 3 F numOfDmmyBytes [2:0] $end
$var reg 1 G serMclkEnable_n $end
$var reg 8 H serializerByteBuffer [7:0] $end
$var reg 4 I serializerCycleCount [3:0] $end
$var reg 1 J serializerEnable $end
$upscope $end
$upscope $end
$enddefinitions $end
$comment Show the parameter values. $end
$dumpall
b0 7
b11 6
b100 5
b1 4
b10 3
$end
#0
$dumpvars
0J
b0 I
b0 H
1G
b1 F
b0 E
0D
b0 C
b0 B
b0 A
0@
b0 ?
b0 >
b0 =
bx <
0;
0:
09
b0 8
12
z1
bx 0
b1100110 /
bx .
bx -
0,
1+
1*
1)
b1100110 (
bx '
1&
b0 %
0$
1#
0"
0!
$end
#1000
0+
#2000
1+
#3000
0+
#4000
1+
#5000
0+
#6000
1+
#7000
0+
#8000
1+
0)
#9000
0+
#10000
1+
#11000
0+
#12000
1+
#13000
0+
#14000
1+
#15000
0+
#16000
1+
1)
#17000
0+
#18000
1+
#19000
0+
#20000
1+
#21000
0+
#22000
1+
#23000
0+
#24000
1+
0)
#25000
0+
#26000
1+
#27000
0+
#28000
1+
#29000
0+
#30000
1+
0*
#31000
0+
#32000
b1 C
b0xxxxxxxxxxxxxxxxxxxxxx <
b1100110 =
0&
1+
1)
#33000
0+
#34000
1+
#35000
0+
#36000
1+
#37000
0+
#38000
1+
#39000
0+
#40000
1+
0)
#41000
0+
#42000
1+
#43000
0+
#44000
1+
#45000
0+
#46000
1+
#47000
0+
#48000
b1100110 H
1J
1+
1)
#49000
0#
b1 I
b11001100 E
0G
0+
#50000
1#
1+
#51000
b10 I
1"
b10011000 E
0#
0+
#52000
1#
1+
#53000
b11 I
b110000 E
0#
0+
#54000
1#
1+
#55000
b100 I
0"
b1100000 E
0#
0+
#56000
1#
1+
0)
#57000
b101 I
b11000000 E
0#
0+
#58000
1#
1+
#59000
b110 I
1"
b10000000 E
0#
0+
#60000
1#
1+
#61000
b111 I
b0 E
0#
0+
#62000
1#
1+
#63000
b0 I
1!
0"
0#
0+
#64000
0J
b0 C
1#
1+
1)
#65000
0!
1G
1#
0+
#66000
1+
#67000
0+
#68000
1+
#69000
0+
#70000
1+
#71000
0+
#72000
1+
0)
#73000
0+
#74000
1+
#75000
0+
#76000
1+
#77000
0+
#78000
1+
#79000
0+
#80000
b1 C
1+
1)
#81000
0+
#82000
1+
#83000
0+
#84000
1+
#85000
0+
#86000
1+
#87000
0+
#88000
1+
0)
#89000
0+
#90000
1+
#91000
0+
#92000
1+
#93000
0+
#94000
1+
#95000
0+
#96000
1J
1+
1)
#97000
0#
b1 I
b11001100 E
0G
0+
#98000
1#
1+
#99000
b10 I
1"
b10011000 E
0#
0+
#100000
1#
1+
#101000
b11 I
b110000 E
0#
0+
#102000
1#
1+
#103000
b100 I
0"
b1100000 E
0#
0+
#104000
1#
1+
0)
#105000
b101 I
b11000000 E
0#
0+
#106000
1#
1+
#107000
b110 I
1"
b10000000 E
0#
0+
#108000
1#
1+
#109000
b111 I
b0 E
0#
0+
#110000
1#
1+
#111000
b0 I
1!
0"
0#
0+
#112000
0J
b0 C
1#
1+
1)
#113000
0!
1G
1#
0+
#114000
1+
#115000
0+
#116000
1+
#117000
0+
#118000
1+
#119000
0+
#120000
1+
0)
#121000
0+
#122000
1+
#123000
0+
#124000
1+
#125000
0+
#126000
1+
#127000
0+
#128000
b1 C
1+
1)
#129000
0+
#130000
1+
#131000
0+
#132000
1+
#133000
0+
#134000
1+
#135000
0+
#136000
1+
0)
#137000
0+
#138000
1+
#139000
0+
#140000
1+
#141000
0+
#142000
1+
#143000
0+
#144000
1J
1+
1)
#145000
0#
b1 I
b11001100 E
0G
0+
#146000
1#
1+
#147000
b10 I
1"
b10011000 E
0#
0+
#148000
1#
1+
#149000
b11 I
b110000 E
0#
0+
#150000
1#
1+
#151000
b100 I
0"
b1100000 E
0#
0+
#152000
1#
1+
0)
#153000
b101 I
b11000000 E
0#
0+
#154000
1#
1+
#155000
b110 I
1"
b10000000 E
0#
0+
#156000
1#
1+
#157000
b111 I
b0 E
0#
0+
#158000
1#
1+
#159000
b0 I
1!
0"
0#
0+
#160000
0J
b0 C
1#
1+
1)
#161000
0!
1G
1#
0+
#162000
1+
#163000
0+
#164000
1+
#165000
0+
#166000
1+
#167000
0+
#168000
1+
0)
#169000
0+
#170000
1+
#171000
0+
#172000
1+
#173000
0+
#174000
1+
#175000
0+
#176000
b1 C
1+
1)
#177000
0+
#178000
1+
#179000
0+
#180000
1+
1*
#181000
0+
#182000
1+
#183000
0+
#184000
1+
0)
#185000
0+
#186000
1+
#187000
0+
#188000
1+
#189000
0+
#190000
1+
#191000
0+
#192000
1&
b0 C
1+
1)
